reaktion_next/__init__.py
reaktion_next/actor.py
reaktion_next/contractors.py
reaktion_next/errors.py
reaktion_next/events.py
reaktion_next/exceptions.py
reaktion_next/extension.py
reaktion_next/reference_counter.py
reaktion_next/registry.py
reaktion_next/rekuest.py
reaktion_next/rpc_contract.py
reaktion_next/types.py
reaktion_next/utils.py
reaktion_next/atoms/__init__.py
reaktion_next/atoms/arkitekt.py
reaktion_next/atoms/arkitekt_filter.py
reaktion_next/atoms/base.py
reaktion_next/atoms/errors.py
reaktion_next/atoms/generic.py
reaktion_next/atoms/helpers.py
reaktion_next/atoms/reactive.py
reaktion_next/atoms/template.py
reaktion_next/atoms/transport.py
reaktion_next/atoms/utils.py
reaktion_next/atoms/combination/__init__.py
reaktion_next/atoms/combination/base.py
reaktion_next/atoms/combination/combinelatest.py
reaktion_next/atoms/combination/gate.py
reaktion_next/atoms/combination/withlatest.py
reaktion_next/atoms/combination/zip.py
reaktion_next/atoms/filter/__init__.py
reaktion_next/atoms/filter/all.py
reaktion_next/atoms/operations/__init__.py
reaktion_next/atoms/operations/base.py
reaktion_next/atoms/operations/math.py
reaktion_next/atoms/transformation/__init__.py
reaktion_next/atoms/transformation/base.py
reaktion_next/atoms/transformation/buffer_complete.py
reaktion_next/atoms/transformation/buffer_count.py
reaktion_next/atoms/transformation/chunk.py
reaktion_next/atoms/transformation/filter.py
reaktion_next/atoms/transformation/omit.py
reaktion_next/atoms/transformation/split.py
reaktion_next-0.4.0.dist-info/METADATA
reaktion_next-0.4.0.dist-info/WHEEL
reaktion_next-0.4.0.dist-info/licenses/LICENSE
reaktion_next-0.4.0.dist-info/RECORD
