Metadata-Version: 2.4
Name: reaktion-next
Version: 0.4.0
Summary: rpc and node backbone
Author-email: jhnnsrs <jhnnsrs@gmail.com>
License-Expression: GPL-3.0-or-later
License-File: LICENSE
Requires-Python: <4.0,>=3.11
Requires-Dist: fluss-next>=0.7.0
Requires-Dist: rath>=3.5.1
Requires-Dist: rekuest-next>=0.12.2
